simplempi/__init__.py
simplempi/parfor.py
simplempi/simpleMPI.py
simplempi-0.1.5.dist-info/LICENSE
simplempi-0.1.5.dist-info/METADATA
simplempi-0.1.5.dist-info/WHEEL
simplempi-0.1.5.dist-info/top_level.txt
simplempi-0.1.5.dist-info/RECORD
