Metadata-Version: 2.1
Name: simplempi
Version: 0.1.5
Summary: A wrapper around mpi4py that offers simple scattering of iterable objects.
Home-page: https://github.com/taobrienlbl/simplempi
Author: Travis A. O'Brien
Author-email: obrienta@iu.edu
License: BSD-3-Clause
Platform: UNKNOWN
Classifier: Development Status :: 3 - Alpha
Classifier: Intended Audience :: Developers
Classifier: License :: OSI Approved :: BSD License
Classifier: Programming Language :: Python :: 3
Classifier: Programming Language :: Python :: 3.6
Classifier: Programming Language :: Python :: 3.7
Classifier: Programming Language :: Python :: 3.8
Classifier: Programming Language :: Python :: 3.9
Classifier: Programming Language :: Python :: 3.10
Classifier: Programming Language :: Python :: 3.11
Classifier: Programming Language :: Python :: 3.12
Requires-Dist: mpi4py
